.gitignore
CHANGES.txt
README.txt
setup.py
docs/LICENSE.GPL
docs/LICENSE.txt
plone/__init__.py
plone.portlet.viewlet.egg-info/PKG-INFO
plone.portlet.viewlet.egg-info/SOURCES.txt
plone.portlet.viewlet.egg-info/dependency_links.txt
plone.portlet.viewlet.egg-info/entry_points.txt
plone.portlet.viewlet.egg-info/namespace_packages.txt
plone.portlet.viewlet.egg-info/not-zip-safe
plone.portlet.viewlet.egg-info/requires.txt
plone.portlet.viewlet.egg-info/top_level.txt
plone/portlet/__init__.py
plone/portlet/viewlet/__init__.py
plone/portlet/viewlet/configure.zcml
plone/portlet/viewlet/portlet.py
plone/portlet/viewlet/profiles/default/portlets.xml
plone/portlet/viewlet/tests/__init__.py
plone/portlet/viewlet/tests/base.py
plone/portlet/viewlet/tests/test_portlet_viewlet.py