Metadata-Version: 1.0
Name: plone.portlet.viewlet
Version: 0.4
Summary: A portlet that displays a viewlet for Plone.
Home-page: http://plone.org
Author: Laurence Rowe
Author-email: plone-developers@lists.sourceforge.net
License: GPL
Keywords: plone portlet
Platform: UNKNOWN
Classifier: Framework :: Plone
Classifier: Programming Language :: Python
